pttp/__init__.py
pttp/__main__.py
pttp-0.0.3.dist-info/METADATA
pttp-0.0.3.dist-info/WHEEL
pttp-0.0.3.dist-info/entry_points.txt
pttp-0.0.3.dist-info/licenses/LICENSE
pttp-0.0.3.dist-info/RECORD
