Metadata-Version: 2.1
Name: pttp
Version: 0.0.3
Summary: Python tracing profiler
Project-URL: Documentation, https://github.com/vivster7/pttp#readme
Project-URL: Issues, https://github.com/vivster7/pttp/issues
Project-URL: Source, https://github.com/vivster7/pttp
Author-email: Vivek Dasari <vivster7@gmail.com>
License-Expression: MIT
License-File: LICENSE
Classifier: Development Status :: 4 - Beta
Classifier: Programming Language :: Python
Classifier: Programming Language :: Python :: 3.7
Classifier: Programming Language :: Python :: 3.8
Classifier: Programming Language :: Python :: 3.9
Classifier: Programming Language :: Python :: 3.10
Classifier: Programming Language :: Python :: 3.11
Classifier: Programming Language :: Python :: Implementation :: CPython
Classifier: Programming Language :: Python :: Implementation :: PyPy
Requires-Python: >=3.7
